odoo/addons/account_invoice_report_hide_delivery_address/README.rst
odoo/addons/account_invoice_report_hide_delivery_address/__init__.py
odoo/addons/account_invoice_report_hide_delivery_address/__manifest__.py
odoo/addons/account_invoice_report_hide_delivery_address/i18n/ca_ES.po
odoo/addons/account_invoice_report_hide_delivery_address/i18n/es.po
odoo/addons/account_invoice_report_hide_delivery_address/models/__init__.py
odoo/addons/account_invoice_report_hide_delivery_address/models/account_move.py
odoo/addons/account_invoice_report_hide_delivery_address/models/res_company.py
odoo/addons/account_invoice_report_hide_delivery_address/models/res_config_settings.py
odoo/addons/account_invoice_report_hide_delivery_address/models/res_partner.py
odoo/addons/account_invoice_report_hide_delivery_address/report/report_invoice.xml
odoo/addons/account_invoice_report_hide_delivery_address/static/description/icon.png
odoo/addons/account_invoice_report_hide_delivery_address/tests/__init__.py
odoo/addons/account_invoice_report_hide_delivery_address/tests/test_account_invoice_report_hide_delivery_address.py
odoo/addons/account_invoice_report_hide_delivery_address/views/account_move_view.xml
odoo/addons/account_invoice_report_hide_delivery_address/views/res_config_settings_view.xml
odoo/addons/account_invoice_report_hide_delivery_address/views/res_partner_view.xml
odoo_addon_account_invoice_report_hide_delivery_address-18.0.1.0.0.dist-info/METADATA
odoo_addon_account_invoice_report_hide_delivery_address-18.0.1.0.0.dist-info/WHEEL
odoo_addon_account_invoice_report_hide_delivery_address-18.0.1.0.0.dist-info/top_level.txt
odoo_addon_account_invoice_report_hide_delivery_address-18.0.1.0.0.dist-info/RECORD
